[
    {
        "url": "https://raw.githubusercontent.com/MrXtron/CS/builds/Bollyzone.cs3",
        "status": 1,
        "version": 3,
        "name": "Bollyzone",
        "internalName": "Bollyzone",
        "authors": [
            "MrXtron"
        ],
        "description": "BollyZone",
        "fileSize": 31130,
        "repositoryUrl": "https://github.com/MrXtron/CS",
        "language": "hi",
        "tvTypes": [
            "Movie",
            "TvSeries"
        ],
        "iconUrl": "https://raw.githubusercontent.com/MrXtron/CSF/refs/heads/main/Icons/BollyZone.png",
        "apiVersion": 1,
        "fileHash": "sha256-51f88e639cf536ecf3d4be7ab8e08f44750e164842919a960b2310897c7d7316",
        "jarFileSize": 129161,
        "jarUrl": "https://raw.githubusercontent.com/MrXtron/CS/builds/Bollyzone.jar",
        "jarHash": "sha256-c6109badc5a7fb18499cfe51c06708f810f576ea7b82bd71d144a8303c4d653b"
    },
    {
        "url": "https://raw.githubusercontent.com/MrXtron/CS/builds/DudeFilms.cs3",
        "status": 1,
        "version": 7,
        "name": "DudeFilms",
        "internalName": "DudeFilms",
        "authors": [
            "Phisher98"
        ],
        "description": "Watch Movies & TvSeries (Multi-Lang)",
        "fileSize": 68827,
        "repositoryUrl": "https://github.com/MrXtron/CS",
        "language": "hi",
        "tvTypes": [
            "Movie",
            "TvSeries"
        ],
        "iconUrl": "https://raw.githubusercontent.com/MrXtron/CSF/refs/heads/main/Icons/dudefilms.png",
        "apiVersion": 1,
        "fileHash": "sha256-987915bafbe1a80bb4e5360d5dc6aceb23e0ddcee739094be221e9b687135934"
    },
    {
        "url": "https://raw.githubusercontent.com/MrXtron/CS/builds/HdHub4U.cs3",
        "status": 1,
        "version": 9,
        "name": "HdHub4U",
        "internalName": "HdHub4U",
        "authors": [
            "Phisher98"
        ],
        "fileSize": 79963,
        "repositoryUrl": "https://github.com/MrXtron/CS",
        "language": "hi",
        "tvTypes": [
            "Movie",
            "TvSeries",
            "Anime"
        ],
        "iconUrl": "https://raw.githubusercontent.com/MrXtron/CSF/refs/heads/main/Icons/HDHUB.png",
        "apiVersion": 1,
        "fileHash": "sha256-e4aa4a90e613ffb01ed0bd50c9eaf4dbd6e0fc2308f190c32d92a25c6933e8a9"
    },
    {
        "url": "https://raw.githubusercontent.com/MrXtron/CS/builds/HdMovie2.cs3",
        "status": 1,
        "version": 6,
        "name": "HdMovie2",
        "internalName": "HdMovie2",
        "authors": [
            "-"
        ],
        "description": "Hdmovie2",
        "fileSize": 40604,
        "repositoryUrl": "https://github.com/MrXtron/CS",
        "language": "hi",
        "tvTypes": [
            "TvSeries",
            "Movie"
        ],
        "iconUrl": "https://raw.githubusercontent.com/MrXtron/CSF/refs/heads/main/Icons/HDMovie2.png",
        "apiVersion": 1,
        "fileHash": "sha256-0e6eda854dc07ec291d2b94646dc41e227f73937500a88773466ebadaa097596",
        "jarFileSize": 201552,
        "jarUrl": "https://raw.githubusercontent.com/MrXtron/CS/builds/HdMovie2.jar",
        "jarHash": "sha256-2dfb3bad20d599652c61627155d18b09c8e1475366d8e795f2dcdd3ec5ecda99"
    },
    {
        "url": "https://raw.githubusercontent.com/MrXtron/CS/builds/MovieBoxProvider.cs3",
        "status": 1,
        "version": 6,
        "name": "MovieBoxProvider",
        "internalName": "MovieBoxProvider",
        "authors": [
            "NivinCNC,Phisher98"
        ],
        "description": "Multi Language Movies and Series Provider",
        "fileSize": 69367,
        "repositoryUrl": "https://github.com/MrXtron/CS",
        "language": "hi",
        "tvTypes": [
            "Movie",
            "TvSeries"
        ],
        "iconUrl": "https://raw.githubusercontent.com/MrXtron/CSF/refs/heads/main/Icons/MovieBox.png",
        "apiVersion": 1,
        "fileHash": "sha256-0ca1d1856d5f74f28d453e95239cf05ef222b051daed3f357a6081921aae6297"
    },
    {
        "url": "https://raw.githubusercontent.com/MrXtron/CS/builds/MultiMoviesProvider.cs3",
        "status": 1,
        "version": 49,
        "name": "MultiMoviesProvider",
        "internalName": "MultiMoviesProvider",
        "authors": [
            "Phisher98"
        ],
        "description": "Indian Multi-language HD Provider",
        "fileSize": 46866,
        "repositoryUrl": "https://github.com/MrXtron/CS",
        "language": "hi",
        "tvTypes": [
            "Movie",
            "TvSeries",
            "Anime"
        ],
        "iconUrl": "https://raw.githubusercontent.com/MrXtron/CSF/refs/heads/main/Icons/MultiMoviesProvider.png",
        "apiVersion": 1,
        "fileHash": "sha256-d5046539fed6d5f5a39201f9c461830edc66ac5d8ba5e08e2b6a68b2c615a25e",
        "jarFileSize": 199511,
        "jarUrl": "https://raw.githubusercontent.com/MrXtron/CS/builds/MultiMoviesProvider.jar",
        "jarHash": "sha256-34438e82f2b2443fdb8adeb3f35d2ce63c462c43ea4fdd17676eec6cf30c049f"
    },
    {
        "url": "https://raw.githubusercontent.com/MrXtron/CS/builds/PRMovies.cs3",
        "status": 1,
        "version": 8,
        "name": "PRMovies",
        "internalName": "PRMovies",
        "authors": [
            " "
        ],
        "fileSize": 17841,
        "repositoryUrl": "https://github.com/MrXtron/CS",
        "language": "hi",
        "tvTypes": [
            "TvSeries",
            "Movie"
        ],
        "iconUrl": "https://raw.githubusercontent.com/MrXtron/CSF/refs/heads/main/Icons/PrMovies.png",
        "apiVersion": 1,
        "fileHash": "sha256-f5ad825a7e06612c74457336f90928c0c268a6fce073618d024ed9821cacb45a"
    },
    {
        "url": "https://raw.githubusercontent.com/MrXtron/CS/builds/RadioIndiaProvider.cs3",
        "status": 1,
        "version": 3,
        "name": "RadioIndiaProvider",
        "internalName": "RadioIndiaProvider",
        "authors": [
            "NivinCNC"
        ],
        "description": "Radio India Provider",
        "fileSize": 17617,
        "repositoryUrl": "https://github.com/MrXtron/CS",
        "language": "ta",
        "tvTypes": [
            "Live"
        ],
        "iconUrl": "https://cdn.mytuner.mobi/static/ctr/icons/App_192x192/in.png",
        "apiVersion": 1,
        "fileHash": "sha256-24b2d78095058c18a4d98e989a56276abfa146f2849996e6864f54075ce8fb6d"
    },
    {
        "url": "https://raw.githubusercontent.com/MrXtron/CS/builds/RogMovies.cs3",
        "status": 1,
        "version": 4,
        "name": "RogMovies",
        "internalName": "RogMovies",
        "authors": [
            "MrXtron"
        ],
        "description": "Indian Content",
        "fileSize": 44408,
        "repositoryUrl": "https://github.com/MrXtron/CS",
        "language": "hi",
        "tvTypes": [
            "TvSeries",
            "Movie",
            "AsianDrama",
            "Anime"
        ],
        "iconUrl": "https://raw.githubusercontent.com/MrXtron/CSF/refs/heads/main/Icons/RogMovies.png",
        "apiVersion": 1,
        "fileHash": "sha256-4a9ebe2cfce1b780b2c57096a6d134b48c23cf9842d14a0b917d5145d67768fc"
    },
    {
        "url": "https://raw.githubusercontent.com/MrXtron/CS/builds/ToonHub.cs3",
        "status": 1,
        "version": 10,
        "name": "ToonHub",
        "internalName": "ToonHub",
        "authors": [
            "MrXtron"
        ],
        "description": "ToonHub4u Multi Language",
        "fileSize": 23213,
        "repositoryUrl": "https://github.com/MrXtron/CS",
        "language": "hi",
        "tvTypes": [
            "AnimeMovie",
            "Anime",
            "Cartoon"
        ],
        "iconUrl": "https://toonhub4u.me/wp-content/uploads/2024/02/Untitled.png",
        "apiVersion": 1,
        "fileHash": "sha256-2665c13ddc469283e51598921a6f3eebf6fdeec023013be7595bc1644e89d718",
        "jarFileSize": 88933,
        "jarUrl": "https://raw.githubusercontent.com/MrXtron/CS/builds/ToonHub.jar",
        "jarHash": "sha256-cc95d057f338b2aa15f7973fb286c9e198ef56a0c93a72e00c9009cd17b3005e"
    }
]